LICENSE
MANIFEST.in
README.rst
setup.cfg
setup.py
versioneer.py
tpDcc/__init__.py
tpDcc/dccs/__init__.py
tpDcc/dccs/max/__init__.py
tpDcc/dccs/max/__logging__.ini
tpDcc/dccs/max/__version__.py
tpDcc/dccs/max/_version.py
tpDcc/dccs/max/dcc.py
tpDcc/dccs/max/loader.py
tpDcc/dccs/max/core/__init__.py
tpDcc/dccs/max/core/animation.py
tpDcc/dccs/max/core/constants.py
tpDcc/dccs/max/core/curves.py
tpDcc/dccs/max/core/directory.py
tpDcc/dccs/max/core/gui.py
tpDcc/dccs/max/core/helpers.py
tpDcc/dccs/max/core/name.py
tpDcc/dccs/max/core/node.py
tpDcc/dccs/max/core/rig.py
tpDcc/dccs/max/core/scene.py
tpDcc/dccs/max/core/skin.py
tpDcc/dccs/max/core/transform.py
tpDcc/dccs/max/core/viewport.py
tpDcc/dccs/max/maxplus/__init__.py
tpDcc/dccs/max/maxplus/helpers.py
tpDcc/dccs/max/maxplus/scene.py
tpDcc/dccs/max/ui/__init__.py
tpDcc/dccs/max/ui/dialog.py
tpDcc/dccs/max/ui/window.py
tpDcc_dccs_max.egg-info/PKG-INFO
tpDcc_dccs_max.egg-info/SOURCES.txt
tpDcc_dccs_max.egg-info/dependency_links.txt
tpDcc_dccs_max.egg-info/not-zip-safe
tpDcc_dccs_max.egg-info/requires.txt
tpDcc_dccs_max.egg-info/top_level.txt