Metadata-Version: 2.1
Name: tpDcc-dccs-max
Version: 0.0.4
Summary: 3ds Max implementation for tpDcc. Utils functions to work with 3ds Max Python APIs.
Home-page: https://github.com/tpDcc/tpDcc-dccs-max
Author: Tomas Poveda
Author-email: tpovedatd@gmail.com
License: MIT
Platform: UNKNOWN
Provides-Extra: dev
Provides-Extra: test
